recipys/App.py
recipys/ArgParser.py
recipys/ConfigFile.py
recipys/ConsolePrinter.py
recipys/ProgressBar.py
recipys/RecipeFetcher.py
recipys/Scraper.py
recipys/__init__.py
recipys/constants.py
recipys/request_wait.py
recipys/types.py
recipys-1.2.0.dist-info/LICENSE
recipys-1.2.0.dist-info/METADATA
recipys-1.2.0.dist-info/WHEEL
recipys-1.2.0.dist-info/entry_points.txt
recipys-1.2.0.dist-info/top_level.txt
recipys-1.2.0.dist-info/RECORD
