Metadata-Version: 2.1
Name: recipys
Version: 1.2.0
Summary: Get recipes instantly with this CLI tool. Choose specific meals or ingredients to cater to your appetite!
Home-page: https://github.com/gmso/recipys
Author: Germán Mené Santa Olaya
Author-email: german.mene@gmail.com
License: UNKNOWN
Platform: UNKNOWN
Classifier: Programming Language :: Python :: 3
Classifier: Programming Language :: Python :: 3.7
Classifier: Programming Language :: Python :: 3.8
Classifier: Programming Language :: Python :: 3.9
Classifier: License :: OSI Approved :: MIT License
Classifier: Operating System :: OS Independent
Classifier: Environment :: Console
Requires-Python: >3.7.0
Requires-Dist: beautifulsoup4
Requires-Dist: requests
Requires-Dist: rich
